auto-metamask/__init__.py
auto-metamask/__version__.py
auto-metamask/core.py
auto_metamask/__init__.py
auto_metamask/__version__.py
auto_metamask/core.py
dapp-automation/__init__.py
auto_metamask-0.2.4.dist-info/LICENSE
auto_metamask-0.2.4.dist-info/METADATA
auto_metamask-0.2.4.dist-info/WHEEL
auto_metamask-0.2.4.dist-info/top_level.txt
auto_metamask-0.2.4.dist-info/RECORD
